{   
    "name": "config keys to translate",
    "comments": "Liste les textes de ConfigOptions à traduire",
    "version": "0.1",
    "timestamp": "2024-09-03 14:35:26",
    "config_keys_to_translate": [
        "page_patient_disable_default_message",
        "page_patient_title",
        "page_patient_subtitle",
        "page_patient_qrcode_data",
        "page_patient_validation_message",
        "page_patient_confirmation_message",
        "ticket_header",
        "ticket_message",
        "ticket_footer",
        "phone_title",
        "phone_line1",
        "phone_line2",
        "phone_line3",
        "phone_line4",
        "phone_line5",
        "phone_line6",
        "announce_call_sound",
        "announce_ongoing_text",
        "announce_call_text",
        "announce_text_down_patients",
        "page_patient_interface_validate_print",
        "page_patient_interface_validate_scan",
        "page_patient_interface_validate_cancel",
        "page_patient_interface_done_print",
        "page_patient_interface_done_extend",
        "page_patient_interface_done_back"
    ]
}