{
    "name": "config_backup",
    "type": "default",
    "version": "0.35",
    "timestamp": "2024-12-08 16:35:26",
    "comments": "Version de test",
        "configurations": {
            "network_adress": "http://192.168.86.221:5000",
            "pharmacy_name": "Pharmacie Sainte-Agathe",
            "start_rabbitmq": false,
            "use_rabbitmq": false,
            "cron_delete_patient_table_activated": true,
            "cron_transfer_patient_to_history": true,
            "cron_delete_patient_table_hour": "00:00",
            "cron_delete_announce_calls_activated": true,
            "cron_delete_announce_calls_hour": "00:00",
            "algo_activate": true,
            "algo_overtaken_limit": 3,
            "numbering_by_activity": true,
            "printer": false,
            "printer_width": 42,
            "add_paper": false,
            "admin_colors": "slate",
            "announce_sound": true,
            "announce_alert": true,
            "announce_player": "web",
            "announce_alert_filename": "beep.wav",
            "announce_style": "default",
            "voice_google_key": null,
            "announce_title": "Bienvenue à la pharmacie Sainte-Agathe",
            "announce_title_size": 50,
            "announce_subtitle": "Merci de vous enregistrer sur la borne à l'entrée",
            "announce_text_up_patients": "En appel",
            "announce_text_up_patients_display": "always",
            "announce_text_up_patients_size": 50,
            "announce_text_down_patients": "Prenez un ticket",
            "announce_text_down_patients_display": "empty",
            "announce_text_down_patients_size": 50,
            "announce_call_text": "Le patient {N} est invité au comptoir {C}",
            "announce_call_text_size": 50,
            "announce_call_text_transition": "slide",
            "announce_ongoing_display": true,
            "announce_ongoing_text": "Comptoir {C} : Patient {N}",
            "announce_next_patients_display": false,
            "announce_next_patients_text": "Prochains patients :",
            "announce_next_patients_alignment": "center",
            "announce_call_sound": "Le patient {N} est invité au comptoir {C}",
            "announce_call_translation": "vo",
            "announce_infos_display": true,
            "announce_infos_display_time": 30,
            "announce_infos_transition": "slide",
            "announce_gallery_folders": "static/galleries",
            "announce_infos_gallery": "[]", 
            "announce_infos_mix_folders": true,
            "announce_infos_width": 800,
            "announce_infos_height": 800,
            "counter_order": "order",
            "music_volume": 50,
            "music_announce_volume": 20,
            "music_announce_action": "pause",
            "music_spotify": false,
            "music_spotify_user": "your spotify user",
            "music_spotify_key": "your spotify key",
            "page_patient_structure": "full",
            "page_patient_disable_button": true,
            "page_patient_disable_default_message": "Cette activité est momentanément indisponible. Adressez-vous à notre équipe pour plus d'informations.",
            "page_patient_title": "Bienvenue à la pharmacie Sainte-Agathe",
            "page_patient_subtitle": "Afin de faciliter votre prise en charge, merci de vous enregistrer sur cette borne.",
            "page_patient_validation_message": "Vous avez choisi : {A}",
            "page_patient_confirmation_message": "Votre demande est bien prise en charge. Votre numéro est {N}",
            "page_patient_qrcode_display": true,
            "page_patient_qrcode_web_page": true,
            "page_patient_qrcode_data": "Numéro d'appel : {N}",
            "page_patient_qrcode_display_specific_message": true,
            "page_patient_print_ticket_display": true,
            "page_patient_end_timer": 5,
            "page_patient_display_button_scan": true,
            "page_patient_display_scan_explanation": true,
            "page_patient_display_specific_message": true,
            "page_patient_display_translations": true,
            "page_patient_interface_validate_print": "Imprimer un ticket",
            "page_patient_interface_validate_scan": "Scanner le code avec le téléphone",
            "page_patient_interface_scan_explanation": "Ou scanner le QR-Code avec votre téléphone",
            "page_patient_interface_validate_cancel": "Annuler",
            "page_patient_interface_done_print": "Imprimer",
            "page_patient_interface_done_extend": "Prolonger",
            "page_patient_interface_done_back": "Retour à la page d'accueil",
            "page_patient_direct_print": false,
            "page_patient_print_after_scan": false,
            "page_patient_print_after_print": true,
            "page_patient_timer_activity_inactive": 10,
            "page_patient_button_print_ticket_display_picture": true,
            "page_patient_button_cancel_display_picture": true,
            "page_patient_button_print_ticket_picture": "",
            "page_patient_button_cancel_picture": "",
            "ticket_header": "Bienvenue à la pharmacie Sainte-Agathe",
            "ticket_header_printer": "",
            "ticket_message": "Votre numéro d'appel : {N}",
            "ticket_message_printer": "",
            "ticket_footer": "Afin d'améliorer les temps d'attente, l'ordre de passage peut être légèrement différent de l'ordre d'arrivée.",
            "ticket_footer_printer": "",
            "ticket_display_specific_message": true,
            "mail_server": "",
            "mail_port": "",
            "mail_username": "",
            "mail_password": "",
            "mail_default_sender": "",
            "mail_use_tls": true,
            "mail_use_ssl": false,
            "phone_center": true,
            "phone_title": "Bienvenue à la pharmacie Sainte-Agathe",
            "phone_line1": "Votre numéro d'appel :",
            "phone_line2": "{N}",
            "phone_line3": "Votre demande :",
            "phone_line4": "{A}",
            "phone_line5": "Afin d'améliorer les temps d'attente, l'ordre de passage peut être légèrement différent de l'ordre d'arrivée.",
            "phone_line6": "Nous vous appelerons à votre tour.",
            "phone_display_specific_message": true,
            "phone_display_your_turn": true,
            "phone_your_turn_line1":"",
            "phone_your_turn_line2":"",
            "phone_your_turn_line3":"",
            "phone_your_turn_line4":"",
            "phone_your_turn_line5":"",
            "phone_your_turn_line6":"",
            "security_login_admin": true,
            "security_login_counter": true,
            "security_login_screen": true,
            "security_login_patient": true,
            "security_remember_duration": 30
    }
}